dataflake/__init__.py
dataflake/coverage.xml
dataflake/cover/coverage_html.js
dataflake/cover/dataflake_ldapconnection___init___py.html
dataflake/cover/dataflake_ldapconnection_connection_py.html
dataflake/cover/dataflake_ldapconnection_interfaces_py.html
dataflake/cover/dataflake_ldapconnection_utils_py.html
dataflake/cover/index.html
dataflake/cover/jquery.ba-throttle-debounce.min.js
dataflake/cover/jquery.hotkeys.js
dataflake/cover/jquery.isonscreen.js
dataflake/cover/jquery.min.js
dataflake/cover/jquery.tablesorter.min.js
dataflake/cover/keybd_closed.png
dataflake/cover/keybd_open.png
dataflake/cover/status.json
dataflake/cover/style.css
dataflake/ldapconnection/__init__.py
dataflake/ldapconnection/connection.py
dataflake/ldapconnection/interfaces.py
dataflake/ldapconnection/utils.py
dataflake/ldapconnection/tests/__init__.py
dataflake/ldapconnection/tests/base.py
dataflake/ldapconnection/tests/dummy.py
dataflake/ldapconnection/tests/test_connection_basic.py
dataflake/ldapconnection/tests/test_connection_connect.py
dataflake/ldapconnection/tests/test_connection_delete.py
dataflake/ldapconnection/tests/test_connection_insert.py
dataflake/ldapconnection/tests/test_connection_modify.py
dataflake/ldapconnection/tests/test_connection_search.py
dataflake/ldapconnection/tests/test_connection_servers.py
dataflake/ldapconnection/tests/test_connection_unicode.py
dataflake/ldapconnection/tests/test_utils.py
dataflake.ldapconnection-2.1.dist-info/METADATA
dataflake.ldapconnection-2.1.dist-info/RECORD
dataflake.ldapconnection-2.1.dist-info/WHEEL
dataflake.ldapconnection-2.1.dist-info/top_level.txt
