Metadata-Version: 2.1
Name: dataflake.ldapconnection
Version: 2.1
Summary: LDAP connection library
Home-page: https://github.com/dataflake/dataflake.ldapconnection
Author: Agendaless Consulting and Jens Vagelpohl
Author-email: jens@dataflake.org
License: ZPL 2.1
Keywords: ldap ldapv3
Platform: UNKNOWN
Classifier: Development Status :: 5 - Production/Stable
Classifier: Intended Audience :: Developers
Classifier: License :: OSI Approved :: Zope Public License
Classifier: Operating System :: OS Independent
Classifier: Programming Language :: Python :: 2
Classifier: Programming Language :: Python :: 2.7
Classifier: Programming Language :: Python :: 3
Classifier: Programming Language :: Python :: 3.5
Classifier: Programming Language :: Python :: 3.6
Classifier: Programming Language :: Python :: 3.7
Classifier: Programming Language :: Python :: Implementation :: CPython
Classifier: Topic :: Software Development :: Libraries :: Python Modules
Classifier: Topic :: System :: Systems Administration :: Authentication/Directory :: LDAP
Provides-Extra: docs
Provides-Extra: testing
Requires-Dist: setuptools
Requires-Dist: six
Requires-Dist: pyldap
Requires-Dist: zope.interface
Requires-Dist: dataflake.cache
Requires-Dist: dataflake.fakeldap
Provides-Extra: docs
Requires-Dist: sphinx; extra == 'docs'
Requires-Dist: repoze.sphinx.autointerface; extra == 'docs'
Provides-Extra: testing
Requires-Dist: nose; extra == 'testing'
Requires-Dist: coverage; extra == 'testing'
